{
  "id": "brisbane-2025",
  "name": "Battle of the Tech Bands - Brisbane 2025",
  "date": "2025-09-04T08:30:00Z",
  "location": "The Triffid",
  "address": "7-9 Stratton Street, Newstead QLD 4006, Australia",
  "tickets": "https://www.moshtix.com.au/v2/event/battle-of-the-tech-bands-%E2%80%93-powered-by-jumbo-interactive/182735",
  "is_active": false,
  "bands": [
    {
      "name": "The ShipRex",
      "description": "Rex Software",
      "order": 1
    },
    {
      "name": "Jumbo Band",
      "description": "Jumbo Interactive",
      "order": 2
    },
    {
      "name": "Epsonics",
      "description": "Epsilon",
      "order": 3
    },
    {
      "name": "Off the Record",
      "description": "For the Record",
      "order": 4
    }
  ]
}

